{"uuid":"36a1669e355e9c21d9a6289601670dd5aa2a4eae","bioAsHtml":"<p>Paul entered the realm of functional and type-level programming three years ago when he was caught by a Scala meetup. After that, he started doing Scala professionally as a Data Engineer for the social network XING. There he works on recommender systems and the ontology infrastructure which are serving requests of millions of users every day.</p>\n","acceptedTalks":[{"talkType":"Conference","track":"Type & Functional Programming","links":[{"href":"https://cfp.scala.io/api/conferences/ScalaIOFR2018/talks/MMB-4947","rel":"https://cfp.scala.io/api/profile/talk","title":"More details about this talk"},{"href":"https://cfp.scala.io/api/conferences/ScalaIOFR2018/speakers/36a1669e355e9c21d9a6289601670dd5aa2a4eae","rel":"https://cfp.scala.io/api/profile/speaker","title":"Paul Heymann"}],"id":"MMB-4947","title":"Let's derive HTTP clients from types"}],"company":"XING SE","bio":"Paul entered the realm of functional and type-level programming three years ago when he was caught by a Scala meetup. After that, he started doing Scala professionally as a Data Engineer for the social network XING. There he works on recommender systems and the ontology infrastructure which are serving requests of millions of users every day.","lastName":"Heymann","firstName":"Paul","blog":"https://github.com/pheymann","avatarURL":"https://www.xing.com/img/users/d/a/2/4c614478a.22361740,3.256x256.jpg","twitter":null,"lang":"fr"}